xlrd/__init__.py
xlrd/biffh.py
xlrd/book.py
xlrd/compdoc.py
xlrd/formatting.py
xlrd/formula.py
xlrd/info.py
xlrd/sheet.py
xlrd/timemachine.py
xlrd/xldate.py
xlrd/xlsx.py
xlrd/examples/namesdemo.xls
xlrd/examples/xlrdnameAPIdemo.py
xlrd_with_formulas-1.0.0.data/scripts/runxlrd.py
xlrd_with_formulas-1.0.0.dist-info/DESCRIPTION.rst
xlrd_with_formulas-1.0.0.dist-info/METADATA
xlrd_with_formulas-1.0.0.dist-info/RECORD
xlrd_with_formulas-1.0.0.dist-info/WHEEL
xlrd_with_formulas-1.0.0.dist-info/metadata.json
xlrd_with_formulas-1.0.0.dist-info/top_level.txt
